netrun/oauth/__init__.py
netrun/oauth/exceptions.py
netrun/oauth/factory.py
netrun/oauth/py.typed
netrun/oauth/token_manager.py
netrun/oauth/adapters/__init__.py
netrun/oauth/adapters/base.py
netrun/oauth/adapters/docusign.py
netrun/oauth/adapters/dropbox.py
netrun/oauth/adapters/google.py
netrun/oauth/adapters/hubspot.py
netrun/oauth/adapters/mailchimp.py
netrun/oauth/adapters/meta.py
netrun/oauth/adapters/microsoft.py
netrun/oauth/adapters/quickbooks.py
netrun/oauth/adapters/salesforce.py
netrun/oauth/adapters/slack.py
netrun/oauth/adapters/xero.py
netrun/oauth/adapters/zoom.py
netrun_oauth/__init__.py
netrun_oauth/exceptions.py
netrun_oauth/factory.py
netrun_oauth/token_manager.py
netrun_oauth/adapters/__init__.py
netrun_oauth/adapters/base.py
netrun_oauth/adapters/docusign.py
netrun_oauth/adapters/dropbox.py
netrun_oauth/adapters/google.py
netrun_oauth/adapters/hubspot.py
netrun_oauth/adapters/mailchimp.py
netrun_oauth/adapters/meta.py
netrun_oauth/adapters/microsoft.py
netrun_oauth/adapters/quickbooks.py
netrun_oauth/adapters/salesforce.py
netrun_oauth/adapters/slack.py
netrun_oauth/adapters/xero.py
netrun_oauth/adapters/zoom.py
netrun_oauth-2.0.0.dist-info/METADATA
netrun_oauth-2.0.0.dist-info/WHEEL
netrun_oauth-2.0.0.dist-info/RECORD
