Metadata-Version: 2.4
Name: netrun-oauth
Version: 2.0.0
Summary: Reusable OAuth 2.0 adapters for multi-tenant SaaS applications
Project-URL: Homepage, https://netrunsystems.com
Project-URL: Documentation, https://github.com/netrunsystems/netrun-service-library
Project-URL: Repository, https://github.com/netrunsystems/netrun-service-library
Project-URL: Issues, https://github.com/netrunsystems/netrun-service-library/issues
Author-email: Netrun Systems <support@netrunsystems.com>
License: MIT
Keywords: authentication,google,microsoft,multi-tenant,oauth,oauth2,saas,salesforce
Classifier: Development Status :: 5 - Production/Stable
Classifier: Intended Audience :: Developers
Classifier: License :: OSI Approved :: MIT License
Classifier: Programming Language :: Python :: 3
Classifier: Programming Language :: Python :: 3.8
Classifier: Programming Language :: Python :: 3.9
Classifier: Programming Language :: Python :: 3.10
Classifier: Programming Language :: Python :: 3.11
Classifier: Programming Language :: Python :: 3.12
Classifier: Topic :: Internet :: WWW/HTTP :: Session
Classifier: Topic :: Security
Classifier: Topic :: Software Development :: Libraries :: Python Modules
Requires-Python: >=3.8
Requires-Dist: cryptography>=41.0.0
Requires-Dist: httpx>=0.25.0
Requires-Dist: netrun-core>=2.0.0
Provides-Extra: all
Requires-Dist: azure-identity>=1.14.0; extra == 'all'
Requires-Dist: azure-keyvault-secrets>=4.7.0; extra == 'all'
Requires-Dist: black>=23.0.0; extra == 'all'
Requires-Dist: mypy>=1.0.0; extra == 'all'
Requires-Dist: pytest-asyncio>=0.21.0; extra == 'all'
Requires-Dist: pytest-cov>=4.0.0; extra == 'all'
Requires-Dist: pytest>=7.0.0; extra == 'all'
Requires-Dist: ruff>=0.1.0; extra == 'all'
Provides-Extra: azure
Requires-Dist: azure-identity>=1.14.0; extra == 'azure'
Requires-Dist: azure-keyvault-secrets>=4.7.0; extra == 'azure'
Provides-Extra: dev
Requires-Dist: black>=23.0.0; extra == 'dev'
Requires-Dist: mypy>=1.0.0; extra == 'dev'
Requires-Dist: pytest-asyncio>=0.21.0; extra == 'dev'
Requires-Dist: pytest-cov>=4.0.0; extra == 'dev'
Requires-Dist: pytest>=7.0.0; extra == 'dev'
Requires-Dist: ruff>=0.1.0; extra == 'dev'
